venty/__init__.py
venty/_dummy.py
venty/aggregate_root.py
venty/aggregate_store.py
venty/aggregate_store_test.py
venty/entity.py
venty/event_channel.py
venty/event_channel_test.py
venty/event_producer.py
venty/event_producer_test.py
venty/event_store.py
venty/http_event_channel.py
venty/http_event_channel_test.py
venty/in_memory_event_channel.py
venty/in_memory_event_channel_test.py
venty/in_memory_event_store.py
venty/in_memory_event_store_test.py
venty/py.typed
venty/settings.py
venty/settings_test.py
venty/sql_event_store.py
venty/sql_event_store_test.py
venty/strong_types.py
venty/strong_types_test.py
venty/timing.py
venty/timing_test.py
venty/pydantic_integration/__init__.py
venty/pydantic_integration/event_producer.py
venty/pydantic_integration/event_producer_test.py
venty-4.0.0.dist-info/LICENSE
venty-4.0.0.dist-info/METADATA
venty-4.0.0.dist-info/WHEEL
venty-4.0.0.dist-info/top_level.txt
venty-4.0.0.dist-info/RECORD
