Metadata-Version: 2.1
Name: venty
Version: 4.0.0
Summary: Venty
Home-page: https://github.com/sasha-tkachev/venty
Author: Alexander Tkachev
Author-email: sasha64sasha@gmail.com
License: UNKNOWN
Keywords: cloudevents,cloudevents[pydantic],ce,cloud,events,event,rest
Platform: UNKNOWN
Classifier: Intended Audience :: Information Technology
Classifier: Intended Audience :: System Administrators
Classifier: Intended Audience :: Developers
Classifier: License :: OSI Approved :: Apache Software License
Classifier: Development Status :: 5 - Production/Stable
Classifier: Operating System :: OS Independent
Classifier: Programming Language :: Python :: 3
Classifier: Programming Language :: Python :: 3.8
Classifier: Programming Language :: Python :: 3.9
Classifier: Programming Language :: Python :: 3.10
Classifier: Programming Language :: Python :: 3.11
Classifier: Programming Language :: Python :: 3.12
License-File: LICENSE
Requires-Dist: cloudevents
Requires-Dist: more-itertools
Provides-Extra: http
Requires-Dist: requests ; extra == 'http'
Provides-Extra: pydantic
Requires-Dist: pydantic ; extra == 'pydantic'
Provides-Extra: sql
Requires-Dist: sqlalchemy ; extra == 'sql'
